EPACT/__init__.py
EPACT/dataset/__init__.py
EPACT/dataset/batch_converter.py
EPACT/dataset/data.py
EPACT/model/__init__.py
EPACT/model/coembedding.py
EPACT/model/module.py
EPACT/model/pretrained.py
EPACT/model/utils.py
EPACT/trainer/__init__.py
EPACT/trainer/base.py
EPACT/trainer/binding_trainer.py
EPACT/trainer/interact_trainer.py
EPACT/trainer/plm_trainer.py
EPACT/utils/__init__.py
EPACT/utils/encoding.py
EPACT/utils/misc.py
EPACT/utils/sampling.py
EPACT/utils/tokenizer.py
epact-0.1.1.dist-info/LICENSE
epact-0.1.1.dist-info/METADATA
epact-0.1.1.dist-info/WHEEL
epact-0.1.1.dist-info/top_level.txt
epact-0.1.1.dist-info/RECORD
