Metadata-Version: 2.1
Name: epact
Version: 0.1.1
Summary: Epitope-anchored contrastive transfer learning for paired CD8+ T Cell receptor-antigen Rrcognition
Author-email: Yumeng Zhang <zhangyumeng1@sjtu.edu.cn>
Project-URL: Homepage, https://github.com/zhangyumeng1sjtu/EPACT
Project-URL: Issues, https://github.com/zhangyumeng1sjtu/EPACT/issues
Classifier: Programming Language :: Python :: 3
Classifier: License :: OSI Approved :: GNU General Public License v3 (GPLv3)
Classifier: Operating System :: OS Independent
Requires-Python: >=3.10
License-File: LICENSE
Requires-Dist: torch ~=2.0
Requires-Dist: biopython ==1.81
Requires-Dist: easydict ==1.11
Requires-Dist: PyYAML ==6.0
Requires-Dist: numpy ~=1.25
Requires-Dist: pandas ~=2.0
Requires-Dist: scikit-learn ~=1.3
Requires-Dist: scipy ~=1.11
Requires-Dist: tensorboard ~=2.13
Requires-Dist: tqdm ~=4.65
Requires-Dist: warmup-scheduler ==0.3
